rajnikantmahato/__init__.py
rajnikantmahato/rajnikantmahato.py
rajnikantmahato-1.2.dist-info/LICENSE
rajnikantmahato-1.2.dist-info/METADATA
rajnikantmahato-1.2.dist-info/WHEEL
rajnikantmahato-1.2.dist-info/top_level.txt
rajnikantmahato-1.2.dist-info/RECORD
