Metadata-Version: 2.1
Name: rajnikantmahato
Version: 1.2
Summary: personal module
Home-page: https://github.com/pypa/rajnikantmahato
Author: rajnikantmahato,Simplehacker1 , Simplehacker01 , Simplehacker02, sm02present
Author-email: rajnikantmahato33435@gmail.com
Project-URL: Bug Tracker, https://github.com/pypa/rajnikantmahato/issues
Classifier: Programming Language :: Python :: 3
Classifier: Programming Language :: Python :: 3.5
Classifier: Programming Language :: Python :: 3.7
Classifier: License :: OSI Approved :: MIT License
Classifier: Operating System :: OS Independent
Requires-Python: >=3.5
License-File: LICENSE
